hatariTools/__init__.py
hatariTools/utils.py
hatariTools/examples/json/templates.json
hatariTools/examples/notebooks/p1_phreeqcModel.ipynb
hatariTools/examples/notebooks/p2_cropRecognition.ipynb
hatariTools/geospatialIA/__init__.py
hatariTools/geospatialIA/cropRecognition.py
hatariTools/geospatialIA/geologicalModeling.py
hatariTools/geospatialTools/rasterTools.py
hatariTools/modelEngines/__init__.py
hatariTools/modelEngines/phrTools.py
hataritools-0.0.6.dist-info/licenses/LICENSE
hataritools-0.0.6.dist-info/METADATA
hataritools-0.0.6.dist-info/WHEEL
hataritools-0.0.6.dist-info/top_level.txt
hataritools-0.0.6.dist-info/RECORD
