Metadata-Version: 2.4
Name: hatariTools
Version: 0.0.6
Summary: The Hatari repository for a bunch of Python tools in water resources.
Author-email: Saul Montoya <saulmontoya@hatarilabs.com>
License-Expression: MIT
Project-URL: Homepage, https://github.com/hatarilabs/hatariTools
Keywords: MODFLOW,groundwater,hydrogeology
Requires-Python: >=3.9
License-File: LICENSE
Requires-Dist: fiona>=1.9.6
Requires-Dist: geopandas>=1.0.0
Requires-Dist: numpy<2.2.5,>=1.26.4
Requires-Dist: pandas>=2.2.2
Requires-Dist: scipy<1.15.2,>=1.13.0
Requires-Dist: shapely>=1.8.2
Requires-Dist: rasterio>=1.3.8
Requires-Dist: flopy>=3.9.2
Requires-Dist: tqdm>=4.67.1
Requires-Dist: paramiko>=3.5.1
Requires-Dist: scikit-image>=0.25.2
Requires-Dist: scikit-learn>=1.7.0
Requires-Dist: seaborn>=0.13.2
Provides-Extra: 3dvisualization
Requires-Dist: vtk>=9.5.2; extra == "3dvisualization"
Requires-Dist: pyvista>=0.46.3; extra == "3dvisualization"
Dynamic: license-file
